native_sparse_attention_pytorch/__init__.py
native_sparse_attention_pytorch/compress_networks.py
native_sparse_attention_pytorch/native_sparse_attention.py
native_sparse_attention_pytorch/tensor_typing.py
native_sparse_attention_pytorch/transformer.py
native_sparse_attention_pytorch/triton_native_sparse_attention.py
native_sparse_attention_pytorch-0.2.3.dist-info/METADATA
native_sparse_attention_pytorch-0.2.3.dist-info/WHEEL
native_sparse_attention_pytorch-0.2.3.dist-info/licenses/LICENSE
native_sparse_attention_pytorch-0.2.3.dist-info/RECORD
