Metadata-Version: 2.4
Name: native-sparse-attention-pytorch
Version: 0.2.3
Summary: Native Sparse Attention
Project-URL: Homepage, https://pypi.org/project/native-sparse-attention-pytorch/
Project-URL: Repository, https://github.com/lucidrains/native-sparse-attention-pytorch
Author-email: Phil Wang <lucidrains@gmail.com>
License: MIT License
License-File: LICENSE
Keywords: artificial intelligence,deep learning,efficient attention
Classifier: Development Status :: 4 - Beta
Classifier: Intended Audience :: Developers
Classifier: License :: OSI Approved :: MIT License
Classifier: Programming Language :: Python :: 3.9
Classifier: Topic :: Scientific/Engineering :: Artificial Intelligence
Requires-Python: >=3.9
Requires-Dist: einops>=0.8.1
Requires-Dist: einx>=0.3.0
Requires-Dist: jaxtyping
Requires-Dist: local-attention>=1.11.1
Requires-Dist: rotary-embedding-torch
Requires-Dist: torch>=2.5
Provides-Extra: examples
Requires-Dist: tqdm; extra == 'examples'
Requires-Dist: wandb; extra == 'examples'
Provides-Extra: test
Requires-Dist: pytest; extra == 'test'
Requires-Dist: tqdm; extra == 'test'
